setup.cfg
setup.py
xgboostwithwarmstart/__init__.py
xgboostwithwarmstart/xgboost_with_warm_start.py
xgboostwithwarmstart.egg-info/PKG-INFO
xgboostwithwarmstart.egg-info/SOURCES.txt
xgboostwithwarmstart.egg-info/dependency_links.txt
xgboostwithwarmstart.egg-info/requires.txt
xgboostwithwarmstart.egg-info/top_level.txt