Metadata-Version: 1.1
Name: xgboostwithwarmstart
Version: 0.1.0
Summary: XGBoost can warm start !!!!
Home-page: https://github.com/SoluMilken/xgboostwithwarmstart
Author: ianlini and solumilken
Author-email: UNKNOWN
License: UNKNOWN
Platform: UNKNOWN
Classifier: Development Status :: 1 - Planning
Classifier: Intended Audience :: Developers
Classifier: Topic :: Utilities
Classifier: Programming Language :: Python :: 2
Classifier: Programming Language :: Python :: 2.6
Classifier: Programming Language :: Python :: 2.7
Classifier: Programming Language :: Python :: 3
Classifier: Programming Language :: Python :: 3.3
Classifier: Programming Language :: Python :: 3.4
Classifier: Programming Language :: Python :: 3.5
